featurebyte_freeware-0.2.23.data/data/featurebyte_freeware/feature_job_analysis/templates/report.html
featurebyte_freeware-0.2.23.dist-info/RECORD
featurebyte_freeware-0.2.23.dist-info/WHEEL
featurebyte_freeware-0.2.23.dist-info/top_level.txt
featurebyte_freeware-0.2.23.dist-info/METADATA
featurebyte_freeware/__init__.cpython-312-darwin.so
featurebyte_freeware/logging.cpython-312-darwin.so
featurebyte_freeware/feature_job_analysis/__init__.cpython-312-darwin.so
featurebyte_freeware/feature_job_analysis/stats.cpython-312-darwin.so
featurebyte_freeware/feature_job_analysis/plots.cpython-312-darwin.so
featurebyte_freeware/feature_job_analysis/database.cpython-312-darwin.so
featurebyte_freeware/feature_job_analysis/reports.cpython-312-darwin.so
featurebyte_freeware/feature_job_analysis/tiles.cpython-312-darwin.so
featurebyte_freeware/feature_job_analysis/core.cpython-312-darwin.so
featurebyte_freeware/feature_job_analysis/analysis.cpython-312-darwin.so
featurebyte_freeware/feature_job_analysis/util.cpython-312-darwin.so
featurebyte_freeware/feature_job_analysis/outlier.cpython-312-darwin.so
featurebyte_freeware/feature_job_analysis/schema.cpython-312-darwin.so
featurebyte_freeware/feature_job_analysis/templates/report.html
featurebyte_freeware/feature_job_analysis/sql/__init__.cpython-312-darwin.so
featurebyte_freeware/feature_job_analysis/sql/bigquery/__init__.cpython-312-darwin.so
featurebyte_freeware/feature_job_analysis/sql/bigquery/templates.cpython-312-darwin.so
featurebyte_freeware/feature_job_analysis/sql/snowflake/__init__.cpython-312-darwin.so
featurebyte_freeware/feature_job_analysis/sql/snowflake/templates.cpython-312-darwin.so
featurebyte_freeware/feature_job_analysis/sql/spark/__init__.cpython-312-darwin.so
featurebyte_freeware/feature_job_analysis/sql/spark/templates.cpython-312-darwin.so
