Metadata-Version: 2.4
Name: featurebyte_freeware
Version: 0.2.23
Summary: Free utilities from FeatureByte
Author-email: FeatureByte <it-admin@featurebyte.com>
Classifier: Development Status :: 3 - Alpha
Classifier: Intended Audience :: Developers
Classifier: Operating System :: OS Independent
Classifier: Topic :: Software Development :: Libraries :: Python Modules
Classifier: Programming Language :: Python :: 3
Classifier: Programming Language :: Python :: 3.10
Classifier: Programming Language :: Python :: 3.11
Classifier: Programming Language :: Python :: 3.12
Requires-Python: <4,>=3.10
Requires-Dist: Jinja2>=3.1.2
Requires-Dist: matplotlib>=3.5.2
Requires-Dist: pandas>=1.5.3
Requires-Dist: scipy>=1.10.0
Requires-Dist: numpy>=1.26.4
